DictTTL/DefaultDictTTL.py
DictTTL/DictTTL.py
DictTTL/OrderedDictTTL.py
DictTTL/__init__.py
DictTTL/benchmark.py
DictTTL/files/DefaultDictTTL_class.py
DictTTL/files/DictTTL_class.py
DictTTL/files/OrderedDictTTL_class.py
DictTTL/files/__init__.py
DictTTL/tests/__init__.py
DictTTL/tests/unit/__init__.py
DictTTL/tests/unit/test_DefaultDictTTL.py
DictTTL/tests/unit/test_DictTTL.py
DictTTL/tests/unit/test_OrderedDictTTL.py
dictttl-0.1.6.dist-info/DESCRIPTION.rst
dictttl-0.1.6.dist-info/METADATA
dictttl-0.1.6.dist-info/RECORD
dictttl-0.1.6.dist-info/WHEEL
dictttl-0.1.6.dist-info/metadata.json
dictttl-0.1.6.dist-info/top_level.txt
tests/__init__.py
tests/unit/__init__.py
tests/unit/test_DefaultDictTTL.py
tests/unit/test_DictTTL.py
tests/unit/test_OrderedDictTTL.py
