Metadata-Version: 2.0
Name: dictttl
Version: 0.1.6
Summary: Dictionary with TTL attached to the keys
Home-page: https://github.com/srivassid/DictTTL
Author: Siddharth Srivastava
Author-email: s.srivas@hotmail.com
License: MIT
Platform: UNKNOWN
